sifflet_sdk/__init__.py
sifflet_sdk/config.py
sifflet_sdk/constants.py
sifflet_sdk/errors.py
sifflet_sdk/logger.py
sifflet_sdk/apis/__init__.py
sifflet_sdk/apis/base.py
sifflet_sdk/client/__init__.py
sifflet_sdk/client/api_client.py
sifflet_sdk/client/api_response.py
sifflet_sdk/client/configuration.py
sifflet_sdk/client/exceptions.py
sifflet_sdk/client/rest.py
sifflet_sdk/client/api/__init__.py
sifflet_sdk/client/api/access_token_api.py
sifflet_sdk/client/api/agent_proxy_api.py
sifflet_sdk/client/api/ai_agent_api.py
sifflet_sdk/client/api/ai_chat_api.py
sifflet_sdk/client/api/ai_predictions_api.py
sifflet_sdk/client/api/alerting_hook_api.py
sifflet_sdk/client/api/asset_api.py
sifflet_sdk/client/api/assets_api.py
sifflet_sdk/client/api/automation_api.py
sifflet_sdk/client/api/aws_api.py
sifflet_sdk/client/api/calendars_api.py
sifflet_sdk/client/api/collaboration_tool_api.py
sifflet_sdk/client/api/collaboration_tool_webhook_api.py
sifflet_sdk/client/api/cookies_api.py
sifflet_sdk/client/api/credentials_api.py
sifflet_sdk/client/api/custom_metadata_api.py
sifflet_sdk/client/api/dashboard_api.py
sifflet_sdk/client/api/data_product_api.py
sifflet_sdk/client/api/datapoint_qualification_api.py
sifflet_sdk/client/api/dataset_api.py
sifflet_sdk/client/api/dataset_field_api.py
sifflet_sdk/client/api/dataset_field_tag_prediction_api.py
sifflet_sdk/client/api/datasource_api.py
sifflet_sdk/client/api/datasource_connection_api.py
sifflet_sdk/client/api/dbt_impact_analysis_api.py
sifflet_sdk/client/api/dbt_integration_api.py
sifflet_sdk/client/api/declarative_assets_and_lineage_api.py
sifflet_sdk/client/api/domain_api.py
sifflet_sdk/client/api/domains_api.py
sifflet_sdk/client/api/external_catalog_api.py
sifflet_sdk/client/api/feature_api.py
sifflet_sdk/client/api/idp_api.py
sifflet_sdk/client/api/incident_api.py
sifflet_sdk/client/api/integration_api.py
sifflet_sdk/client/api/lineage_api.py
sifflet_sdk/client/api/mail_api.py
sifflet_sdk/client/api/metadata_jobs_api.py
sifflet_sdk-0.4.3.dist-info/licenses/LICENSE
sifflet_sdk-0.4.3.dist-info/METADATA
sifflet_sdk-0.4.3.dist-info/WHEEL
sifflet_sdk-0.4.3.dist-info/top_level.txt
sifflet_sdk-0.4.3.dist-info/RECORD
