Metadata-Version: 2.4
Name: sifflet_sdk
Version: 0.4.3
Summary: Sifflet sdk
Home-page: https://www.siffletdata.com/
Author: Sifflet
Author-email: support@siffletdata.com
Classifier: Programming Language :: Python :: 3
Classifier: Operating System :: OS Independent
Requires-Python: >=3.7
License-File: LICENSE
Requires-Dist: PyJWT<3.0.0,>=1.7.0
Requires-Dist: requests
Requires-Dist: python-dateutil
Requires-Dist: pyyaml
Requires-Dist: pydantic<3,>=2
Requires-Dist: typing-extensions<5.0.0,>=4.7.1
Dynamic: author
Dynamic: author-email
Dynamic: classifier
Dynamic: description
Dynamic: description-content-type
Dynamic: home-page
Dynamic: license-file
Dynamic: requires-dist
Dynamic: requires-python
Dynamic: summary
